{
	"key": "group_6152e6e948c08",
	"title": "SMIN Optionen",
	"fields": [
		{
			"key": "field_6152e6f61cd3b",
			"label": "Logo",
			"name": "logo",
			"type": "image",
			"instructions": "",
			"required": 0,
			"conditional_logic": 0,
			"wrapper": {
				"width": "",
				"class": "",
				"id": ""
			},
			"return_format": "url",
			"preview_size": "medium",
			"library": "all",
			"min_width": "",
			"min_height": "",
			"min_size": "",
			"max_width": "",
			"max_height": "",
			"max_size": "",
			"mime_types": ""
		},
		{
			"key": "field_6152esss6f61cdss3b",
			"label": "Favicon",
			"name": "favicon",
			"type": "image",
			"instructions": "",
			"required": 0,
			"conditional_logic": 0,
			"wrapper": {
				"width": "",
				"class": "",
				"id": ""
			},
			"return_format": "url",
			"preview_size": "medium",
			"library": "all",
			"min_width": "",
			"min_height": "",
			"min_size": "",
			"max_width": "",
			"max_height": "",
			"max_size": "",
			"mime_types": ""
		},
		{
			"key": "field_6152eabb43660",
			"label": "Header Buttons",
			"name": "header_buttons",
			"type": "repeater",
			"instructions": "",
			"required": 0,
			"conditional_logic": 0,
			"wrapper": {
				"width": "",
				"class": "",
				"id": ""
			},
			"collapsed": "",
			"min": 0,
			"max": 0,
			"layout": "table",
			"button_label": "",
			"sub_fields": [
				{
					"key": "field_6152eacd43661",
					"label": "Bild",
					"name": "bild",
					"type": "image",
					"instructions": "",
					"required": 0,
					"conditional_logic": 0,
					"wrapper": {
						"width": "",
						"class": "",
						"id": ""
					},
					"return_format": "url",
					"preview_size": "medium",
					"library": "all",
					"min_width": "",
					"min_height": "",
					"min_size": "",
					"max_width": "",
					"max_height": "",
					"max_size": "",
					"mime_types": ""
				},
				{
					"key": "field_6152ead443662",
					"label": "Link",
					"name": "link",
					"type": "link",
					"instructions": "",
					"required": 0,
					"conditional_logic": 0,
					"wrapper": {
						"width": "",
						"class": "",
						"id": ""
					},
					"return_format": "url"
				}
			]
		},
		{
			"key": "field_61532a06796da",
			"label": "Kontaktdaten",
			"name": "kontaktdaten",
			"type": "wysiwyg",
			"instructions": "",
			"required": 0,
			"conditional_logic": 0,
			"wrapper": {
				"width": "",
				"class": "",
				"id": ""
			},
			"default_value": "",
			"tabs": "all",
			"toolbar": "full",
			"media_upload": 1,
			"delay": 0
		},
		{
			"key": "field_61532a06sss796da",
			"label": "Farbe",
			"name": "farbe",
			"type": "color_picker",
			"instructions": "",
			"required": 0,
			"conditional_logic": 0,
			"wrapper": {
				"width": "",
				"class": "",
				"id": ""
			},
			"default_value": "",
			"tabs": "all",
			"toolbar": "full",
			"media_upload": 1,
			"delay": 0
		},
		{
			"key": "field_61532a06ssssss796da",
			"label": "Farbe",
			"name": "farbe_dunkel",
			"type": "color_picker",
			"instructions": "",
			"required": 0,
			"conditional_logic": 0,
			"wrapper": {
				"width": "",
				"class": "",
				"id": ""
			},
			"default_value": "",
			"tabs": "all",
			"toolbar": "full",
			"media_upload": 1,
			"delay": 0
		}
	],
	"location": [
		[
			{
				"param": "options_page",
				"operator": "==",
				"value": "smin-optionen"
			}
		]
	],
	"menu_order": 0,
	"position": "normal",
	"style": "seamless",
	"label_placement": "left",
	"instruction_placement": "label",
	"hide_on_screen": "",
	"active": true,
	"description": "",
	"modified": 1632840207
}
